modelframe/__init__.py
modelframe/load_data.py
modelframe/modelframe.py
modelframe/ranef_term.py
modelframe/terms.py
modelframe/data/sleepstudy.csv
modelframe-0.1.1.dist-info/LICENSE
modelframe-0.1.1.dist-info/METADATA
modelframe-0.1.1.dist-info/WHEEL
modelframe-0.1.1.dist-info/top_level.txt
modelframe-0.1.1.dist-info/RECORD
