Metadata-Version: 2.1
Name: modelframe
Version: 0.1.1
Summary: Compute fixed and random effects model matrices in Python
Home-page: https://github.com/dirmeier/modelframe
Author: Simon Dirmeier
Author-email: simon.dirmeier@web.de
License: GPLv3
Keywords: modelframe
Platform: UNKNOWN
Classifier: Development Status :: 3 - Alpha
Classifier: Intended Audience :: Developers
Classifier: License :: OSI Approved :: GNU General Public License v3 (GPLv3)
Classifier: Programming Language :: Python :: 3
Classifier: Programming Language :: Python :: 3.6
Classifier: Programming Language :: Python :: 3.7
Classifier: Programming Language :: Python :: 3.8
Requires-Dist: numpy
Requires-Dist: scipy
Requires-Dist: pandas
Provides-Extra: test
Requires-Dist: tox ; extra == 'test'
